README.md
setup.cfg
setup.py
cloudmonkey/__init__.py
cloudmonkey/cachemaker.py
cloudmonkey/cloudmonkey.py
cloudmonkey/config.py
cloudmonkey/precache.py
cloudmonkey/printer.py
cloudmonkey/requester.py
cloudmonkey.egg-info/PKG-INFO
cloudmonkey.egg-info/SOURCES.txt
cloudmonkey.egg-info/dependency_links.txt
cloudmonkey.egg-info/entry_points.txt
cloudmonkey.egg-info/not-zip-safe
cloudmonkey.egg-info/requires.txt
cloudmonkey.egg-info/top_level.txt